ctf_stream/__init__.py
ctf_stream/cli.py
ctf_stream/client.py
ctf_stream/config.py
ctf_stream/constants.py
ctf_stream/models.py
ctf_stream/py.typed
ctf_stream/processor/__init__.py
ctf_stream/processor/cache.py
ctf_stream/processor/event_processor.py
ctf_stream/publisher/__init__.py
ctf_stream/publisher/redis.py
ctf_stream/resolver/__init__.py
ctf_stream/resolver/token_resolver.py
ctf_stream/ws/__init__.py
ctf_stream/ws/client.py
ctf_stream-0.1.2.dist-info/METADATA
ctf_stream-0.1.2.dist-info/WHEEL
ctf_stream-0.1.2.dist-info/entry_points.txt
ctf_stream-0.1.2.dist-info/licenses/LICENSE
ctf_stream-0.1.2.dist-info/RECORD
