Metadata-Version: 2.4
Name: ctf-stream
Version: 0.1.2
Summary: CTF activity stream SDK for prediction markets.
Project-URL: Homepage, https://github.com/hungraw/ctf-stream
Project-URL: Repository, https://github.com/hungraw/ctf-stream.git
Project-URL: Issues, https://github.com/hungraw/ctf-stream/issues
Author-email: hungraw <hungnguyenraw.main@gmail.com>
License-Expression: MIT
License-File: LICENSE
Keywords: blockchain,ctf,polygon,prediction-markets,trading,websocket
Classifier: Development Status :: 4 - Beta
Classifier: Framework :: AsyncIO
Classifier: Intended Audience :: Developers
Classifier: License :: OSI Approved :: MIT License
Classifier: Operating System :: OS Independent
Classifier: Programming Language :: Python :: 3
Classifier: Programming Language :: Python :: 3.10
Classifier: Programming Language :: Python :: 3.11
Classifier: Programming Language :: Python :: 3.12
Classifier: Topic :: Software Development :: Libraries :: Python Modules
Classifier: Typing :: Typed
Requires-Python: >=3.10
Requires-Dist: aiohttp>=3.9.0
Requires-Dist: eth-abi>=5.0.0
Requires-Dist: eth-utils>=4.0.0
Requires-Dist: redis>=5.0.0
Requires-Dist: rich>=13.0.0
Requires-Dist: typer>=0.12.0
Requires-Dist: websockets>=12.0
Provides-Extra: dev
Requires-Dist: mypy>=1.9.0; extra == 'dev'
Requires-Dist: pytest-asyncio>=0.23.0; extra == 'dev'
Requires-Dist: pytest-cov>=4.0.0; extra == 'dev'
Requires-Dist: pytest>=8.0.0; extra == 'dev'
Requires-Dist: ruff>=0.3.0; extra == 'dev'
